rustfluent-0.1.0a8.dist-info/METADATA
rustfluent-0.1.0a8.dist-info/WHEEL
rustfluent-0.1.0a8.dist-info/licenses/LICENSE
rustfluent/__init__.py
rustfluent/rustfluent.cpython-314-i386-linux-gnu.so
rustfluent-0.1.0a8.dist-info/RECORD
